whitesource_backend/__init__.py
whitesource_backend/app.py
whitesource_backend/component.py
whitesource_backend/model.py
whitesource_backend/paths.py
whitesource_backend/util.py
whitesource_api_extension-0.46.0.dist-info/LICENSE.md
whitesource_api_extension-0.46.0.dist-info/METADATA
whitesource_api_extension-0.46.0.dist-info/WHEEL
whitesource_api_extension-0.46.0.dist-info/top_level.txt
whitesource_api_extension-0.46.0.dist-info/RECORD
