Metadata-Version: 2.1
Name: whitesource-api-extension
Version: 0.46.0
Summary: backend for whitesource-api-extension
Home-page: UNKNOWN
License: UNKNOWN
Platform: UNKNOWN
Requires-Python: >=3.8.*
License-File: LICENSE.md
